parma/__init__.py
parma/core.py
parma/regularisation.py
parma/utils.py
parma-0.2.0.dist-info/AUTHORS.rst
parma-0.2.0.dist-info/LICENSE
parma-0.2.0.dist-info/METADATA
parma-0.2.0.dist-info/WHEEL
parma-0.2.0.dist-info/top_level.txt
parma-0.2.0.dist-info/RECORD
