Metadata-Version: 2.1
Name: parma
Version: 0.2.0
Summary: Multivariate Hermite spline interpolation
Home-page: https://github.com/dougmvieira/parma
Author: Douglas Machado Vieira
Author-email: dougmvieira@gmail.com
License: MIT license
Project-URL: Documentation, https://parma.readthedocs.io/
Project-URL: Changelog, https://parma.readthedocs.io/en/latest/changelog.html
Project-URL: Issue Tracker, https://github.com/dougmvieira/parma/issues
Platform: UNKNOWN
Classifier: Development Status :: 5 - Production/Stable
Classifier: Intended Audience :: Developers
Classifier: License :: OSI Approved :: MIT License
Classifier: Operating System :: Unix
Classifier: Operating System :: POSIX
Classifier: Operating System :: Microsoft :: Windows
Classifier: Programming Language :: Python
Classifier: Programming Language :: Python :: 3
Classifier: Programming Language :: Python :: 3.5
Classifier: Programming Language :: Python :: 3.6
Classifier: Programming Language :: Python :: 3.7
Classifier: Programming Language :: Python :: 3.8
Classifier: Programming Language :: Python :: Implementation :: CPython
Classifier: Topic :: Utilities
Requires-Python: >=3.5
Requires-Dist: numpy
Requires-Dist: scipy
